reloadable/__init__.py
reloadable/config.py
reloadable/decorators.py
reloadable-0.1.5.dist-info/DESCRIPTION.rst
reloadable-0.1.5.dist-info/METADATA
reloadable-0.1.5.dist-info/RECORD
reloadable-0.1.5.dist-info/WHEEL
reloadable-0.1.5.dist-info/metadata.json
reloadable-0.1.5.dist-info/top_level.txt
