Metadata-Version: 2.0
Name: reloadable
Version: 0.1.5
Summary: Rerun a function upon failure
Home-page: https://bitbucket.org/sievetech/reloadable
Author: www.sieve.com.br
Author-email: ti@sieve.com.br
License: UNKNOWN
Keywords: reloadable recover decorator loop cli sieve
Platform: UNKNOWN
Classifier: Development Status :: 5 - Production/Stable
Classifier: Environment :: Console
Classifier: Environment :: Web Environment
Classifier: Intended Audience :: Developers
Classifier: Natural Language :: English
Classifier: Topic :: Utilities
Classifier: Programming Language :: Python :: 2.7
Classifier: Programming Language :: Python :: 3.5
Classifier: Programming Language :: Python :: 3.6
Requires-Python: >=2.7, !=3.0.*, !=3.1.*, !=3.2.*, !=3.3.*, !=3.4.*, <4
